funapi/__init__.py
funapi/convert/__init__.py
funapi/convert/convert_openapi.py
funapi/generate/__init__.py
funapi/generate/core.py
funapi-1.0.2.dist-info/LICENSE
funapi-1.0.2.dist-info/METADATA
funapi-1.0.2.dist-info/WHEEL
funapi-1.0.2.dist-info/top_level.txt
funapi-1.0.2.dist-info/RECORD
