Metadata-Version: 2.1
Name: funapi
Version: 1.0.2
Summary: Add your description here
Requires-Python: >=3.8
License-File: LICENSE
Requires-Dist: funutil>=1.0.33
Requires-Dist: openapi-python-client>=0.21.0
